LICENSE
README.md
setup.py
Interface_KB/ASGFunctions.py
Interface_KB/ContractFunctions.py
Interface_KB/DFAFunctions.py
Interface_KB/HelperFunctions.py
Interface_KB/InterfaceObjects.py
Interface_KB/KB_Interface.py
Interface_KB/PerformanceFunctions.py
Interface_KB/__init__.py
Interface_KB.egg-info/PKG-INFO
Interface_KB.egg-info/SOURCES.txt
Interface_KB.egg-info/dependency_links.txt
Interface_KB.egg-info/requires.txt
Interface_KB.egg-info/top_level.txt